mcp_feishu_proj-0.1.8.dist-info/licenses/LICENSE
mcp_server/__init__.py
mcp_server/fsprojclient.py
mcp_server/server.py
mcp_server/test_server.py
mcp_feishu_proj-0.1.8.dist-info/METADATA
mcp_feishu_proj-0.1.8.dist-info/WHEEL
mcp_feishu_proj-0.1.8.dist-info/entry_points.txt
mcp_feishu_proj-0.1.8.dist-info/top_level.txt
mcp_feishu_proj-0.1.8.dist-info/RECORD
