Metadata-Version: 2.4
Name: mcp-feishu-proj
Version: 0.1.8
Summary: 基于MCP协议的飞书项目管理工具
Author-email: "lizhou.zhu" <rolandlivingstone@gmail.com>
Requires-Python: >=3.10
License-File: LICENSE
Requires-Dist: mcp[cli]>=1.4.1
Requires-Dist: python-dotenv>=1.0.1
Requires-Dist: requests>=2.32.3
Dynamic: license-file
